fabrique/__init__.py
fabrique/_main.py
fabrique/export.py
fabrique/gcp_utils.py
fabrique/inspection.py
fabrique/loading.py
fabrique/lora.py
fabrique/sampling.py
fabrique/tokenizer_utils.py
fabrique/training.py
fabrique/utils.py
fabrique/models/__init__.py
fabrique/models/gemma/__init__.py
fabrique/models/gemma/_main.py
fabrique/models/gemma/layers.py
fabrique/models/gemma/load_rules.py
fabrique/models/gemma/loader.py
fabrique/models/gemma/modeling.py
fabrique/models/gemma/modules.py
fabrique/models/gemma/vision.py
fabrique/models/gemma/vision_utils.py
fabrique-0.3.0.dist-info/licenses/LICENSE
fabrique-0.3.0.dist-info/METADATA
fabrique-0.3.0.dist-info/WHEEL
fabrique-0.3.0.dist-info/top_level.txt
fabrique-0.3.0.dist-info/RECORD
