Metadata-Version: 2.4
Name: fabrique
Version: 0.3.0
Summary: Foundation for modern ML research
Requires-Python: >=3.12
License-File: LICENSE
Requires-Dist: flax>=0.12.0
Requires-Dist: gemma>=3.1.0
Requires-Dist: huggingface-hub>=0.33.4
Requires-Dist: jinja2>=3.1.6
Requires-Dist: kauldron==1.3.0
Requires-Dist: multimethod>=2.0
Requires-Dist: optax>=0.2.5
Requires-Dist: safetensors>=0.5.3
Requires-Dist: tokenizers>=0.21.2
Dynamic: license-file
